setup.py
EinSumConv/__init__.py
EinSumConv/delta.py
EinSumConv/eps.py
EinSumConv/findIndex.py
EinSumConv/lists.py
EinSumConv/namingSymbols.py
EinSumConv/renameIndex.py
EinSumConv/tensor.py
EinSumConv/tests.py
EinSumConv.egg-info/PKG-INFO
EinSumConv.egg-info/SOURCES.txt
EinSumConv.egg-info/dependency_links.txt
EinSumConv.egg-info/requires.txt
EinSumConv.egg-info/top_level.txt