Metadata-Version: 1.0
Name: EinSumConv
Version: 0.0.2
Summary: The EinSumConv package builds on sympy and supports calculations according to Einstein summation convention.
Home-page: https://github.com/LindaLinsefors/EinSumConv
Author: Linda Linsefors
Author-email: linda.linsefors@gmail.com
License: BSD
Keywords: einstein summa sympy index tensor
Platform: UNKNOWN
